MANIFEST.in
setup.py
src/fsqio/__init__.py
src/fsqio.pants.buildgen.python.egg-info/PKG-INFO
src/fsqio.pants.buildgen.python.egg-info/SOURCES.txt
src/fsqio.pants.buildgen.python.egg-info/dependency_links.txt
src/fsqio.pants.buildgen.python.egg-info/namespace_packages.txt
src/fsqio.pants.buildgen.python.egg-info/requires.txt
src/fsqio.pants.buildgen.python.egg-info/top_level.txt
src/fsqio.pants.buildgen.python.egg-info/zip-safe
src/fsqio/pants/__init__.py
src/fsqio/pants/buildgen/__init__.py
src/fsqio/pants/buildgen/python/__init__.py
src/fsqio/pants/buildgen/python/buildgen_python.py
src/fsqio/pants/buildgen/python/map_python_exported_symbols.py
src/fsqio/pants/buildgen/python/register.py
src/fsqio/pants/buildgen/python/third_party_map_python.py
src/fsqio/pants/buildgen/python/source_analysis/__init__.py
src/fsqio/pants/buildgen/python/source_analysis/python_import_parser.py